{
  "hash": "1f321a16",
  "browserHash": "1904e0a3",
  "optimized": {
    "react": {
      "src": "../../node_modules/react/index.js",
      "file": "react.js",
      "fileHash": "2c22b6b5",
      "needsInterop": true
    },
    "react-dom/client": {
      "src": "../../node_modules/react-dom/client.js",
      "file": "react-dom_client.js",
      "fileHash": "161763d8",
      "needsInterop": true
    },
    "firebase/auth": {
      "src": "../../node_modules/firebase/auth/dist/esm/index.esm.js",
      "file": "firebase_auth.js",
      "fileHash": "8b730c05",
      "needsInterop": false
    },
    "react-router-dom": {
      "src": "../../node_modules/react-router-dom/dist/index.js",
      "file": "react-router-dom.js",
      "fileHash": "302d68a0",
      "needsInterop": false
    },
    "firebase/app": {
      "src": "../../node_modules/firebase/app/dist/esm/index.esm.js",
      "file": "firebase_app.js",
      "fileHash": "7979f6c2",
      "needsInterop": false
    },
    "styled-components": {
      "src": "../../node_modules/styled-components/dist/styled-components.browser.esm.js",
      "file": "styled-components.js",
      "fileHash": "d82dfd2f",
      "needsInterop": false
    },
    "react-hook-form": {
      "src": "../../node_modules/react-hook-form/dist/index.esm.mjs",
      "file": "react-hook-form.js",
      "fileHash": "360d287b",
      "needsInterop": false
    }
  },
  "chunks": {
    "chunk-DTZIM4EP": {
      "file": "chunk-DTZIM4EP.js"
    },
    "chunk-XA6AFWSX": {
      "file": "chunk-XA6AFWSX.js"
    },
    "chunk-ST3U5LCA": {
      "file": "chunk-ST3U5LCA.js"
    },
    "chunk-DFKQJ226": {
      "file": "chunk-DFKQJ226.js"
    }
  }
}